[
    {
        "id": "obj_1",
        "type": "objective",
        "question": "रामधारी सिंह 'दिनकर' किस वाद के प्रमुख कवि हैं ?",
        "prashna": "रामधारी सिंह 'दिनकर' किस वाद के प्रमुख कवि हैं ?",
        "instructions": "प्रश्न संख्या 1 से 100 तक के प्रत्येक वस्तुनिष्ठ प्रश्न के साथ चार विकल्प दिए गए हैं, जिनमें से कोई एक सही है। इन 100 प्रश्नों में से किन्हीं 50 प्रश्नों के अपने द्वारा चुने गए सही विकल्प को OMR उत्तर-पत्रक पर चिह्नित करें।",
        "options": {
            "A": "प्रयोगवाद",
            "B": "कैप्सूलवाद",
            "C": "उत्तर छायावाद",
            "D": "नकेनवाद"
        },
        "vikalpa": {
            "A": "प्रयोगवाद",
            "B": "कैप्सूलवाद",
            "C": "उत्तर छायावाद",
            "D": "नकेनवाद"
        }
    },
    {
        "id": "obj_2",
        "type": "objective",
        "question": "सच्चिदानंद हीरानंद वात्स्यायन 'अज्ञेय' ने कितने कवियों का चयन कर 'तार सप्तक' को पेश किया ?",
        "prashna": "सच्चिदानंद हीरानंद वात्स्यायन 'अज्ञेय' ने कितने कवियों का चयन कर 'तार सप्तक' को पेश किया ?",
        "instructions": "प्रश्न संख्या 1 से 100 तक के प्रत्येक वस्तुनिष्ठ प्रश्न के साथ चार विकल्प दिए गए हैं, जिनमें से कोई एक सही है। इन 100 प्रश्नों में से किन्हीं 50 प्रश्नों के अपने द्वारा चुने गए सही विकल्प को OMR उत्तर-पत्रक पर चिह्नित करें।",
        "options": {
            "A": "तीन",
            "B": "चार",
            "C": "सात",
            "D": "नौ"
        },
        "vikalpa": {
            "A": "तीन",
            "B": "चार",
            "C": "सात",
            "D": "नौ"
        }
    },
    {
        "id": "obj_3",
        "type": "objective",
        "question": "वीरेन डंगवाल की किस कृति पर 'रघुवीर सहाय स्मृति पुरस्कार' प्राप्त हुआ ?",
        "prashna": "वीरेन डंगवाल की किस कृति पर 'रघुवीर सहाय स्मृति पुरस्कार' प्राप्त हुआ ?",
        "instructions": "प्रश्न संख्या 1 से 100 तक के प्रत्येक वस्तुनिष्ठ प्रश्न के साथ चार विकल्प दिए गए हैं, जिनमें से कोई एक सही है। इन 100 प्रश्नों में से किन्हीं 50 प्रश्नों के अपने द्वारा चुने गए सही विकल्प को OMR उत्तर-पत्रक पर चिह्नित करें।",
        "options": {
            "A": "दुष्चक्र में स्रष्टा",
            "B": "इसी दुनिया में",
            "C": "अमृत प्रभात",
            "D": "घूमता आईना"
        },
        "vikalpa": {
            "A": "दुष्चक्र में स्रष्टा",
            "B": "इसी दुनिया में",
            "C": "अमृत प्रभात",
            "D": "घूमता आईना"
        }
    },
    {
        "id": "obj_4",
        "type": "objective",
        "question": "'रस्क' शब्द का अर्थ है",
        "prashna": "'रस्क' शब्द का अर्थ है",
        "instructions": "प्रश्न संख्या 1 से 100 तक के प्रत्येक वस्तुनिष्ठ प्रश्न के साथ चार विकल्प दिए गए हैं, जिनमें से कोई एक सही है। इन 100 प्रश्नों में से किन्हीं 50 प्रश्नों के अपने द्वारा चुने गए सही विकल्प को OMR उत्तर-पत्रक पर चिह्नित करें।",
        "options": {
            "A": "प्रेम",
            "B": "ईर्ष्या",
            "C": "संबंध",
            "D": "आदर"
        },
        "vikalpa": {
            "A": "प्रेम",
            "B": "ईर्ष्या",
            "C": "संबंध",
            "D": "आदर"
        }
    },
    {
        "id": "obj_5",
        "type": "objective",
        "question": "सींग का बना वाद्ययंत्र क्या कहलाता है ?",
        "prashna": "सींग का बना वाद्ययंत्र क्या कहलाता है ?",
        "instructions": "प्रश्न संख्या 1 से 100 तक के प्रत्येक वस्तुनिष्ठ प्रश्न के साथ चार विकल्प दिए गए हैं, जिनमें से कोई एक सही है। इन 100 प्रश्नों में से किन्हीं 50 प्रश्नों के अपने द्वारा चुने गए सही विकल्प को OMR उत्तर-पत्रक पर चिह्नित करें।",
        "options": {
            "A": "मृदंग",
            "B": "शृंगी",
            "C": "करतााल",
            "D": "झाल"
        },
        "vikalpa": {
            "A": "मृदंग",
            "B": "शृंगी",
            "C": "करतााल",
            "D": "झाल"
        }
    },
    {
        "id": "obj_6",
        "type": "objective",
        "question": "'परसौ' शब्द का अर्थ है",
        "prashna": "'परसौ' शब्द का अर्थ है",
        "instructions": "प्रश्न संख्या 1 से 100 तक के प्रत्येक वस्तुनिष्ठ प्रश्न के साथ चार विकल्प दिए गए हैं, जिनमें से कोई एक सही है। इन 100 प्रश्नों में से किन्हीं 50 प्रश्नों के अपने द्वारा चुने गए सही विकल्प को OMR उत्तर-पत्रक पर चिह्नित करें।",
        "options": {
            "A": "रस बरसाओ",
            "B": "स्पर्श करो",
            "C": "कल के बाद आना",
            "D": "खाना परोसना"
        },
        "vikalpa": {
            "A": "रस बरसाओ",
            "B": "स्पर्श करो",
            "C": "कल के बाद आना",
            "D": "खाना परोसना"
        }
    },
    {
        "id": "obj_7",
        "type": "objective",
        "question": "विराग होने पर कवि घनानंद कहाँ चले गये ?",
        "prashna": "विराग होने पर कवि घनानंद कहाँ चले गये ?",
        "instructions": "प्रश्न संख्या 1 से 100 तक के प्रत्येक वस्तुनिष्ठ प्रश्न के साथ चार विकल्प दिए गए हैं, जिनमें से कोई एक सही है। इन 100 प्रश्नों में से किन्हीं 50 प्रश्नों के अपने द्वारा चुने गए सही विकल्प को OMR उत्तर-पत्रक पर चिह्नित करें।",
        "options": {
            "A": "अयोध्या",
            "B": "काशी",
            "C": "इलाहाबाद",
            "D": "वृंदावन"
        },
        "vikalpa": {
            "A": "अयोध्या",
            "B": "काशी",
            "C": "इलाहाबाद",
            "D": "वृंदावन"
        }
    },
    {
        "id": "obj_8",
        "type": "objective",
        "question": "कवि सुमित्रानंदन पंत समाजवाद से किस दर्शन की ओर प्रवृत्त हुए ?",
        "prashna": "कवि सुमित्रानंदन पंत समाजवाद से किस दर्शन की ओर प्रवृत्त हुए ?",
        "instructions": "प्रश्न संख्या 1 से 100 तक के प्रत्येक वस्तुनिष्ठ प्रश्न के साथ चार विकल्प दिए गए हैं, जिनमें से कोई एक सही है। इन 100 प्रश्नों में से किन्हीं 50 प्रश्नों के अपने द्वारा चुने गए सही विकल्प को OMR उत्तर-पत्रक पर चिह्नित करें।",
        "options": {
            "A": "जैन दर्शन",
            "B": "अरविन्द दर्शन",
            "C": "चैतन्य दर्शन",
            "D": "सांख्य दर्शन"
        },
        "vikalpa": {
            "A": "जैन दर्शन",
            "B": "अरविन्द दर्शन",
            "C": "चैतन्य दर्शन",
            "D": "सांख्य दर्शन"
        }
    },
    {
        "id": "obj_9",
        "type": "objective",
        "question": "'साफा' क्या है ?",
        "prashna": "'साफा' क्या है ?",
        "instructions": "प्रश्न संख्या 1 से 100 तक के प्रत्येक वस्तुनिष्ठ प्रश्न के साथ चार विकल्प दिए गए हैं, जिनमें से कोई एक सही है। इन 100 प्रश्नों में से किन्हीं 50 प्रश्नों के अपने द्वारा चुने गए सही विकल्प को OMR उत्तर-पत्रक पर चिह्नित करें।",
        "options": {
            "A": "छोटा कुरता जिसे संगीतज्ञ पहनते हैं",
            "B": "बैठने के लिए आरामदायक गद्दा",
            "C": "साफ लंबा वस्त्र जिसे नर्तक कंधे से लेकर कमर तक लपेट लेता है",
            "D": "साफ करने की एक विधि"
        },
        "vikalpa": {
            "A": "छोटा कुरता जिसे संगीतज्ञ पहनते हैं",
            "B": "बैठने के लिए आरामदायक गद्दा",
            "C": "साफ लंबा वस्त्र जिसे नर्तक कंधे से लेकर कमर तक लपेट लेता है",
            "D": "साफ करने की एक विधि"
        }
    },
    {
        "id": "obj_10",
        "type": "objective",
        "question": "'आदिम' शब्द का अर्थ है",
        "prashna": "'आदिम' शब्द का अर्थ है",
        "instructions": "प्रश्न संख्या 1 से 100 तक के प्रत्येक वस्तुनिष्ठ प्रश्न के साथ चार विकल्प दिए गए हैं, जिनमें से कोई एक सही है। इन 100 प्रश्नों में से किन्हीं 50 प्रश्नों के अपने द्वारा चुने गए सही विकल्प को OMR उत्तर-पत्रक पर चिह्नित करें।",
        "options": {
            "A": "नया",
            "B": "अतिप्राचीन",
            "C": "पर्याप्त",
            "D": "अपर्याप्त"
        },
        "vikalpa": {
            "A": "नया",
            "B": "अतिप्राचीन",
            "C": "पर्याप्त",
            "D": "अपर्याप्त"
        }
    },
    {
        "id": "obj_11",
        "type": "objective",
        "question": "'राघव बहुत तेज लड़का है' - यह किस विशेषण का उदाहरण है ?",
        "prashna": "'राघव बहुत तेज लड़का है' - यह किस विशेषण का उदाहरण है ?",
        "instructions": "प्रश्न संख्या 1 से 100 तक के प्रत्येक वस्तुनिष्ठ प्रश्न के साथ चार विकल्प दिए गए हैं, जिनमें से कोई एक सही है। इन 100 प्रश्नों में से किन्हीं 50 प्रश्नों के अपने द्वारा चुने गए सही विकल्प को OMR उत्तर-पत्रक पर चिह्नित करें।",
        "options": {
            "A": "तुलनात्मक विशेषण",
            "B": "सार्वनामिक विशेषण",
            "C": "संख्यावाचक विशेषण",
            "D": "प्रविशेषण"
        },
        "vikalpa": {
            "A": "तुलनात्मक विशेषण",
            "B": "सार्वनामिक विशेषण",
            "C": "संख्यावाचक विशेषण",
            "D": "प्रविशेषण"
        }
    },
    {
        "id": "obj_12",
        "type": "objective",
        "question": "'धनी व्यक्ति' - यह किस विशेषण का उदाहरण है ?",
        "prashna": "'धनी व्यक्ति' - यह किस विशेषण का उदाहरण है ?",
        "options": {
            "A": "गुणवाचक",
            "B": "संख्यावाचक",
            "C": "परिमाणवाचक",
            "D": "सार्वनामिक विशेषण"
        },
        "vikalpa": {
            "A": "गुणवाचक",
            "B": "संख्यावाचक",
            "C": "परिमाणवाचक",
            "D": "सार्वनामिक विशेषण"
        },
        "instructions": "In these 100 questions, answer any 50."
    },
    {
        "id": "obj_13",
        "type": "objective",
        "question": "'उसने हरीश को मारा था' - यह किस भूतकाल का उदाहरण है ?",
        "prashna": "'उसने हरीश को मारा था' - यह किस भूतकाल का उदाहरण है ?",
        "options": {
            "A": "सामान्य भूतकाल",
            "B": "आसन्न भूतकाल",
            "C": "पूर्ण भूतकाल",
            "D": "अपूर्ण भूतकाल"
        },
        "vikalpa": {
            "A": "सामान्य भूतकाल",
            "B": "आसन्न भूतकाल",
            "C": "पूर्ण भूतकाल",
            "D": "अपूर्ण भूतकाल"
        }
    },
    {
        "id": "obj_14",
        "type": "objective",
        "question": "निम्न में कौन वाक्य सकर्मक क्रिया का उदाहरण है ?",
        "prashna": "निम्न में कौन वाक्य सकर्मक क्रिया का उदाहरण है ?",
        "options": {
            "A": "सीता पुस्तक पढ़ती है।",
            "B": "बच्चा रोता है।",
            "C": "रमेश बैठा है।",
            "D": "घोड़ा दौड़ता है।"
        },
        "vikalpa": {
            "A": "सीता पुस्तक पढ़ती है।",
            "B": "बच्चा रोता है।",
            "C": "रमेश बैठा है।",
            "D": "घोड़ा दौड़ता है।"
        }
    },
    {
        "id": "obj_15",
        "type": "objective",
        "question": "'माया जाड़े से काँप रही है' - इस वाक्य में कौन कारक है ?",
        "prashna": "'माया जाड़े से काँप रही है' - इस वाक्य में कौन कारक है ?",
        "options": {
            "A": "कर्म कारक",
            "B": "करण कारक",
            "C": "अपादान कारक",
            "D": "अधिकरण कारक"
        },
        "vikalpa": {
            "A": "कर्म कारक",
            "B": "करण कारक",
            "C": "अपादान कारक",
            "D": "अधिकरण कारक"
        }
    },
    {
        "id": "obj_16",
        "type": "objective",
        "question": "किस मात्रिक छंद के पहले और तीसरे चरण में 13-13 तथा दूसरे और चौथे चरण में 11-11 मात्राएँ होती हैं ?",
        "prashna": "किस मात्रिक छंद के पहले और तीसरे चरण में 13-13 तथा दूसरे और चौथे चरण में 11-11 मात्राएँ होती हैं ?",
        "options": {
            "A": "दोहा",
            "B": "सोरठा",
            "C": "चौपाई",
            "D": "रोला"
        },
        "vikalpa": {
            "A": "दोहा",
            "B": "सोरठा",
            "C": "चौपाई",
            "D": "रोला"
        }
    },
    {
        "id": "obj_17",
        "type": "objective",
        "question": "'रहिमन पानी राखिए, बिन पानी सब सून। पानी गए न ऊबरै, मोती मानुस चून ।।' - किस अलंकार का उदाहरण है ?",
        "prashna": "'रहिमन पानी राखिए, बिन पानी सब सून। पानी गए न ऊबरै, मोती मानुस चून ।।' - किस अलंकार का उदाहरण है ?",
        "options": {
            "A": "रूपक",
            "B": "यमक",
            "C": "श्लेष",
            "D": "दीपक"
        },
        "vikalpa": {
            "A": "रूपक",
            "B": "यमक",
            "C": "श्लेष",
            "D": "दीपक"
        }
    },
    {
        "id": "obj_18",
        "type": "objective",
        "question": "स्पर्श व्यंजनों की संख्या कितनी है ?",
        "prashna": "स्पर्श व्यंजनों की संख्या कितनी है ?",
        "options": {
            "A": "32",
            "B": "25",
            "C": "31",
            "D": "29"
        },
        "vikalpa": {
            "A": "32",
            "B": "25",
            "C": "31",
            "D": "29"
        }
    },
    {
        "id": "obj_19",
        "type": "objective",
        "question": "निम्न में कौन वर्ण अल्पप्राण है ?",
        "prashna": "निम्न में कौन वर्ण अल्पप्राण है ?",
        "options": {
            "A": "ङ",
            "B": "ध",
            "C": "ख",
            "D": "झ"
        },
        "vikalpa": {
            "A": "ङ",
            "B": "ध",
            "C": "ख",
            "D": "झ"
        }
    },
    {
        "id": "obj_20",
        "type": "objective",
        "question": "निम्न में कौन महाप्राण व्यंजन है ?",
        "prashna": "निम्न में कौन महाप्राण व्यंजन है ?",
        "options": {
            "A": "प",
            "B": "छ",
            "C": "ब",
            "D": "द"
        },
        "vikalpa": {
            "A": "प",
            "B": "छ",
            "C": "ब",
            "D": "द"
        }
    },
    {
        "id": "obj_21",
        "type": "objective",
        "question": "'देवरानी' शब्द में कौन प्रत्यय है ?",
        "prashna": "'देवरानी' शब्द में कौन प्रत्यय है ?",
        "options": {
            "A": "देवर",
            "B": "आनी",
            "C": "ई",
            "D": "रानी"
        },
        "vikalpa": {
            "A": "देवर",
            "B": "आनी",
            "C": "ई",
            "D": "रानी"
        }
    },
    {
        "id": "obj_22",
        "type": "objective",
        "question": "'चढ़़ाई' शब्द में कौन प्रत्यय है ?",
        "prashna": "'चढ़़ाई' शब्द में कौन प्रत्यय है ?",
        "options": {
            "A": "आई",
            "B": "अइ",
            "C": "ढाई",
            "D": "इ"
        },
        "vikalpa": {
            "A": "आई",
            "B": "अइ",
            "C": "ढाई",
            "D": "इ"
        }
    },
    {
        "id": "obj_23",
        "type": "objective",
        "question": "'सूर्य' किस शब्द का उदाहरण है ?",
        "prashna": "'सूर्य' किस शब्द का उदाहरण है ?",
        "options": {
            "A": "तत्सम",
            "B": "तद्भव",
            "C": "देशज",
            "D": "विदेशज"
        },
        "vikalpa": {
            "A": "तत्सम",
            "B": "तद्भव",
            "C": "देशज",
            "D": "विदेशज"
        }
    },
    {
        "id": "obj_24",
        "type": "objective",
        "question": "'जलज' किस शब्द का उदाहरण है ?",
        "prashna": "'जलज' किस शब्द का उदाहरण है ?",
        "options": {
            "A": "रूढ़",
            "B": "देशज",
            "C": "योगरूढ़",
            "D": "इनमें से कोई नहीं"
        },
        "vikalpa": {
            "A": "रूढ़",
            "B": "देशज",
            "C": "योगरूढ़",
            "D": "इनमें से कोई नहीं"
        }
    },
    {
        "id": "obj_25",
        "type": "objective",
        "question": "'सेना' किस संज्ञा का उदाहरण है ?",
        "prashna": "'सेना' किस संज्ञा का उदाहरण है ?",
        "options": {
            "A": "व्यक्तिवाचक",
            "B": "भाववाचक",
            "C": "जातिवाचक",
            "D": "समूहवाचक"
        },
        "vikalpa": {
            "A": "व्यक्तिवाचक",
            "B": "भाववाचक",
            "C": "जातिवाचक",
            "D": "समूहवाचक"
        }
    },
    {
        "id": "obj_26",
        "type": "objective",
        "question": "'लोहा' किस संज्ञा का उदाहरण है ?",
        "prashna": "'लोहा' किस संज्ञा का उदाहरण है ?",
        "options": {
            "A": "भाववाचक",
            "B": "द्रव्यवाचक",
            "C": "समूहवाचक",
            "D": "व्यक्तिवाचक"
        },
        "vikalpa": {
            "A": "भाववाचक",
            "B": "द्रव्यवाचक",
            "C": "समूहवाचक",
            "D": "व्यक्तिवाचक"
        }
    },
    {
        "id": "obj_27",
        "type": "objective",
        "question": "'सेठ' शब्द का स्त्रीलिंग रूप है",
        "prashna": "'सेठ' शब्द का स्त्रीलिंग रूप है",
        "options": {
            "A": "सेठनी",
            "B": "सेठआइन",
            "C": "सेठानी",
            "D": "सेठी"
        },
        "vikalpa": {
            "A": "सेठनी",
            "B": "सेठआइन",
            "C": "सेठानी",
            "D": "सेठी"
        }
    },
    {
        "id": "obj_28",
        "type": "objective",
        "question": "निम्न में कौन शब्द पुल्लिंग है ?",
        "prashna": "निम्न में कौन शब्द पुल्लिंग है ?",
        "options": {
            "A": "अकाल",
            "B": "आज्ञा",
            "C": "चमक",
            "D": "लिखावट"
        },
        "vikalpa": {
            "A": "अकाल",
            "B": "आज्ञा",
            "C": "चमक",
            "D": "लिखावट"
        }
    },
    {
        "id": "obj_29",
        "type": "objective",
        "question": "'मैं स्वयं देख लूँगा' - किस सर्वनाम का उदाहरण है ?",
        "prashna": "'मैं स्वयं देख लूँगा' - किस सर्वनाम का उदाहरण है ?",
        "options": {
            "A": "निश्चयवाचक",
            "B": "अनिश्चयवाचक",
            "C": "निजवाचक",
            "D": "संबंधवाचक"
        },
        "vikalpa": {
            "A": "निश्चयवाचक",
            "B": "अनिश्चयवाचक",
            "C": "निजवाचक",
            "D": "संबंधवाचक"
        }
    },
    {
        "id": "obj_30",
        "type": "objective",
        "question": "सर्वनाम के कितने भेद होते हैं ?",
        "prashna": "सर्वनाम के कितने भेद होते हैं ?",
        "options": {
            "A": "तीन",
            "B": "चार",
            "C": "पांच",
            "D": "छह"
        },
        "vikalpa": {
            "A": "तीन",
            "B": "चार",
            "C": "पांच",
            "D": "छह"
        }
    },
    {
        "id": "obj_31",
        "type": "objective",
        "question": "'मछली' शीर्षक पाठ में कौन मछली को काटा करता था ?",
        "prashna": "'मछली' शीर्षक पाठ में कौन मछली को काटा करता था ?",
        "options": {
            "A": "लेखक",
            "B": "दीदी",
            "C": "घर का नौकर",
            "D": "माँ"
        },
        "vikalpa": {
            "A": "लेखक",
            "B": "दीदी",
            "C": "घर का नौकर",
            "D": "माँ"
        }
    },
    {
        "id": "obj_32",
        "type": "objective",
        "question": "'आविान्यों' शीर्षक पाठ के लेखक हैं",
        "prashna": "'आविान्यों' शीर्षक पाठ के लेखक हैं",
        "options": {
            "A": "अशोक वाजपेयी",
            "B": "नलिन विलोचन शर्मा",
            "C": "रामविलास शर्मा",
            "D": "हजारी प्रसाद द्विवेदी"
        },
        "vikalpa": {
            "A": "अशोक वाजपेयी",
            "B": "नलिन विलोचन शर्मा",
            "C": "रामविलास शर्मा",
            "D": "हजारी प्रसाद द्विवेदी"
        }
    },
    {
        "id": "obj_33",
        "type": "objective",
        "question": "बिरजू महाराज अपना सबसे बड़ा जज किसको मानते थे ?",
        "prashna": "बिरजू महाराज अपना सबसे बड़ा जज किसको मानते थे ?",
        "options": {
            "A": "बाबूजी को",
            "B": "अम्मा को",
            "C": "ताऊ को",
            "D": "पत्नी को"
        },
        "vikalpa": {
            "A": "बाबूजी को",
            "B": "अम्मा को",
            "C": "ताऊ को",
            "D": "पत्नी को"
        }
    },
    {
        "id": "obj_34",
        "type": "objective",
        "question": "“यदि मनुष्य परिस्थितियों का नियामक नहीं है तो परिस्थितियाँ भी मनुष्य की नियामक नहीं हैं।” यह कथन किस लेखक का है ?",
        "prashna": "“यदि मनुष्य परिस्थितियों का नियामक नहीं है तो परिस्थितियाँ भी मनुष्य की नियामक नहीं हैं।” यह कथन किस लेखक का है ?",
        "options": {
            "A": "हजारी प्रसाद द्विवेदी का",
            "B": "गुणाकर मुले का",
            "C": "रामविलास शर्मा का",
            "D": "मैक्स मूलर का"
        },
        "vikalpa": {
            "A": "हजारी प्रसाद द्विवेदी का",
            "B": "गुणाकर मुले का",
            "C": "रामविलास शर्मा का",
            "D": "मैक्स मूलर का"
        }
    },
    {
        "id": "obj_35",
        "type": "objective",
        "question": "बहादुर पर कड़ा अनुशासन कौन रखता था ?",
        "prashna": "बहादुर पर कड़ा अनुशासन कौन रखता था ?",
        "options": {
            "A": "लेखक",
            "B": "पड़ोसी",
            "C": "किशोर",
            "D": "रिश्तेदार"
        },
        "vikalpa": {
            "A": "लेखक",
            "B": "पड़ोसी",
            "C": "किशोर",
            "D": "रिश्तेदार"
        }
    },
    {
        "id": "obj_36",
        "type": "objective",
        "question": "बादशाह अकबर ने जो सिक्का चलाया था उस पर कौन शब्द अंकित है ?",
        "prashna": "बादशाह अकबर ने जो सिक्का चलाया था उस पर कौन शब्द अंकित है ?",
        "options": {
            "A": "राधा-कृष्ण",
            "B": "सियाराम",
            "C": "कृष्ण-रहीम",
            "D": "रामसीय"
        },
        "vikalpa": {
            "A": "राधा-कृष्ण",
            "B": "सियाराम",
            "C": "कृष्ण-रहीम",
            "D": "रामसीय"
        }
    },
    {
        "id": "obj_37",
        "type": "objective",
        "question": "कालिदास ने क्या कहा था ? 'नाखून क्यों बढ़ते हैं' शीर्षक पाठ के आधार पर उत्तर दें।",
        "prashna": "कालिदास ने क्या कहा था ? 'नाखून क्यों बढ़ते हैं' शीर्षक पाठ के आधार पर उत्तर दें।",
        "options": {
            "A": "सब पुराने अच्छे नहीं होते",
            "B": "सब नए खराब ही नहीं होते",
            "C": "(A) और (B) दोनों",
            "D": "सब पुराने और नए सिर्फ अच्छे होते हैं"
        },
        "vikalpa": {
            "A": "सब पुराने अच्छे नहीं होते",
            "B": "सब नए खराब ही नहीं होते",
            "C": "(A) और (B) दोनों",
            "D": "सब पुराने और नए सिर्फ अच्छे होते हैं"
        }
    },
    {
        "id": "obj_38",
        "type": "objective",
        "question": "स्वामी विवेकानंद ने 'वेदांतियों का भी वेदांती' किसे कहा है ?",
        "prashna": "स्वामी विवेकानंद ने 'वेदांतियों का भी वेदांती' किसे कहा है ?",
        "options": {
            "A": "मैक्स मूलर को",
            "B": "गुणाकर मुले को",
            "C": "कालिदास को",
            "D": "विलियम जोन्स को"
        },
        "vikalpa": {
            "A": "मैक्स मूलर को",
            "B": "गुणाकर मुले को",
            "C": "कालिदास को",
            "D": "विलियम जोन्स को"
        }
    },
    {
        "id": "obj_39",
        "type": "objective",
        "question": "मदन पड़ोसियों के आवारागर्द छोकरों के साथ क्या कर रहा था ?",
        "prashna": "मदन पड़ोसियों के आवारागर्द छोकरों के साथ क्या कर रहा था ?",
        "options": {
            "A": "पतंग उड़ा रहा था",
            "B": "क्रिकेट खेल रहा था",
            "C": "लट्टू नचा रहा था",
            "D": "चोर-सिपाही खेल रहा था"
        },
        "vikalpa": {
            "A": "पतंग उड़ा रहा था",
            "B": "क्रिकेट खेल रहा था",
            "C": "लट्टू नचा रहा था",
            "D": "चोर-सिपाही खेल रहा था"
        }
    },
    {
        "id": "obj_40",
        "type": "objective",
        "question": "राजस्थानी भाषा के सफल कहानीकार कौन हैं ?",
        "prashna": "राजस्थानी भाषा के सफल कहानीकार कौन हैं ?",
        "options": {
            "A": "साँवर दइया",
            "B": "श्रीनिवास",
            "C": "सातकोड़ी होता",
            "D": "सुजाता"
        },
        "vikalpa": {
            "A": "साँवर दइया",
            "B": "श्रीनिवास",
            "C": "सातकोड़ी होता",
            "D": "सुजाता"
        }
    },
    {
        "id": "obj_41",
        "type": "objective",
        "question": "निम्नलिखित में कौन शुद्ध शब्द है ?",
        "prashna": "निम्नलिखित में कौन शुद्ध शब्द है ?",
        "options": {
            "A": "सुचिपत्र",
            "B": "छिपकिली",
            "C": "कुमुदिनी",
            "D": "कठीनायी"
        },
        "vikalpa": {
            "A": "सुचिपत्र",
            "B": "छिपकिली",
            "C": "कुमुदिनी",
            "D": "कठीनायी"
        }
    },
    {
        "id": "obj_42",
        "type": "objective",
        "question": "'पीड़ा' शब्द का विशेषण है",
        "prashna": "'पीड़ा' शब्द का विशेषण है",
        "options": {
            "A": "पीड़ाकु",
            "B": "पीड़ितांक",
            "C": "पीड़ित",
            "D": "पीिड़त"
        },
        "vikalpa": {
            "A": "पीड़ाकु",
            "B": "पीड़ितांक",
            "C": "पीड़ित",
            "D": "पीिड़त"
        }
    },
    {
        "id": "obj_43",
        "type": "objective",
        "question": "'मोह' शब्द का विशेषण है",
        "prashna": "'मोह' शब्द का विशेषण है",
        "options": {
            "A": "मोहालु",
            "B": "मोहित",
            "C": "मोहियालु",
            "D": "माहिर"
        },
        "vikalpa": {
            "A": "मोहालु",
            "B": "मोहित",
            "C": "मोहियालु",
            "D": "माहिर"
        }
    },
    {
        "id": "obj_44",
        "type": "objective",
        "question": "'बुद्ध' शब्द का विशेषण है",
        "prashna": "'बुद्ध' शब्द का विशेषण है",
        "options": {
            "A": "बौद्ध",
            "B": "बुद्धायी",
            "C": "बुद्धिनाई",
            "D": "बाधित"
        },
        "vikalpa": {
            "A": "बौद्ध",
            "B": "बुद्धायी",
            "C": "बुद्धिनाई",
            "D": "बाधित"
        }
    },
    {
        "id": "obj_45",
        "type": "objective",
        "question": "‘अमरजीत आज दिल्ली नहीं गया क्योंकि पानी बरस रहा था’ - यह किस वाक्य का उदाहरण है ?",
        "prashna": "‘अमरजीत आज दिल्ली नहीं गया क्योंकि पानी बरस रहा था’ - यह किस वाक्य का उदाहरण है ?",
        "options": {
            "A": "आज्ञावाचक वाक्य",
            "B": "सरल वाक्य",
            "C": "मिश्रवाक्य",
            "D": "संयुक्त वाक्य"
        },
        "vikalpa": {
            "A": "आज्ञावाचक वाक्य",
            "B": "सरल वाक्य",
            "C": "मिश्रवाक्य",
            "D": "संयुक्त वाक्य"
        }
    },
    {
        "id": "obj_46",
        "type": "objective",
        "question": "निम्न में कौन वाक्य कर्मवाच्य का उदाहरण है ?",
        "prashna": "निम्न में कौन वाक्य कर्मवाच्य का उदाहरण है ?",
        "options": {
            "A": "माधव क्रिकेट खेलता है ।",
            "B": "मोहन के द्वारा दौड़ लगाई गई ।",
            "C": "रमेश पत्र लिखता है ।",
            "D": "मानसी खाना खाती है ।"
        },
        "vikalpa": {
            "A": "माधव क्रिकेट खेलता है ।",
            "B": "मोहन के द्वारा दौड़ लगाई गई ।",
            "C": "रमेश पत्र लिखता है ।",
            "D": "मानसी खाना खाती है ।"
        }
    },
    {
        "id": "obj_47",
        "type": "objective",
        "question": "'अवगत' शब्द में कौन उपसर्ग है ?",
        "prashna": "'अवगत' शब्द में कौन उपसर्ग है ?",
        "options": {
            "A": "अव",
            "B": "अधि",
            "C": "अभि",
            "D": "उत्"
        },
        "vikalpa": {
            "A": "अव",
            "B": "अधि",
            "C": "अभि",
            "D": "उत्"
        }
    },
    {
        "id": "obj_48",
        "type": "objective",
        "question": "'कुख्यात' शब्द में कौन उपसर्ग है ?",
        "prashna": "'कुख्यात' शब्द में कौन उपसर्ग है ?",
        "options": {
            "A": "सु",
            "B": "नि",
            "C": "कु",
            "D": "आ"
        },
        "vikalpa": {
            "A": "सु",
            "B": "नि",
            "C": "कु",
            "D": "आ"
        }
    },
    {
        "id": "obj_49",
        "type": "objective",
        "question": "'उपवाक्य' शब्द में कौन उपसर्ग है ?",
        "prashna": "'उपवाक्य' शब्द में कौन उपसर्ग है ?",
        "options": {
            "A": "अव",
            "B": "अप",
            "C": "अधि",
            "D": "उप"
        },
        "vikalpa": {
            "A": "अव",
            "B": "अप",
            "C": "अधि",
            "D": "उप"
        }
    },
    {
        "id": "obj_50",
        "type": "objective",
        "question": "'वेदना' शब्द में कौन प्रत्यय है ?",
        "prashna": "'वेदना' शब्द में कौन प्रत्यय है ?",
        "options": {
            "A": "वेद",
            "B": "अना",
            "C": "न",
            "D": "अ"
        },
        "vikalpa": {
            "A": "वेद",
            "B": "अना",
            "C": "न",
            "D": "अ"
        }
    },
    {
        "id": "obj_51",
        "type": "objective",
        "question": "'पुरोहित' शब्द का संधि-विच्छेद है",
        "prashna": "'पुरोहित' शब्द का संधि-विच्छेद है",
        "options": {
            "A": "पुर + हित",
            "B": "पुर: + हित",
            "C": "पुरो + हित",
            "D": "पुरा: + हीत"
        },
        "vikalpa": {
            "A": "पुर + हित",
            "B": "पुर: + हित",
            "C": "पुरो + हित",
            "D": "पुरा: + हीत"
        }
    },
    {
        "id": "obj_52",
        "type": "objective",
        "question": "'मध्यालय' शब्द का संधि-विच्छेद है",
        "prashna": "'मध्यालय' शब्द का संधि-विच्छेद है",
        "options": {
            "A": "मध्वा + आलय",
            "B": "मधवा + लय",
            "C": "मधु + आलय",
            "D": "मधु + लय"
        },
        "vikalpa": {
            "A": "मध्वा + आलय",
            "B": "मधवा + लय",
            "C": "मधु + आलय",
            "D": "मधु + लय"
        }
    },
    {
        "id": "obj_53",
        "type": "objective",
        "question": "'पावन' शब्द का संधि-विच्छेद है",
        "prashna": "'पावन' शब्द का संधि-विच्छेद है",
        "options": {
            "A": "पौ + अन",
            "B": "पा + वन",
            "C": "पी + वन",
            "D": "पो + अन"
        },
        "vikalpa": {
            "A": "पौ + अन",
            "B": "पा + वन",
            "C": "पी + वन",
            "D": "पो + अन"
        }
    },
    {
        "id": "obj_54",
        "type": "objective",
        "question": "निम्नलिखित में कौन शब्द व्यंजन संधि का उदाहरण है ?",
        "prashna": "निम्नलिखित में कौन शब्द व्यंजन संधि का उदाहरण है ?",
        "options": {
            "A": "तदाकार",
            "B": "तपोभूमि",
            "C": "देवर्षि",
            "D": "निश्चल"
        },
        "vikalpa": {
            "A": "तदाकार",
            "B": "तपोभूमि",
            "C": "देवर्षि",
            "D": "निश्चल"
        }
    },
    {
        "id": "obj_55",
        "type": "objective",
        "question": "निम्नलिखित में कौन शब्द कर्मधारय समास का उदाहरण है ?",
        "prashna": "निम्नलिखित में कौन शब्द कर्मधारय समास का उदाहरण है ?",
        "options": {
            "A": "परोक्ष",
            "B": "यथाशीघ्र",
            "C": "परमेश्वर",
            "D": "भातदाल"
        },
        "vikalpa": {
            "A": "परोक्ष",
            "B": "यथाशीघ्र",
            "C": "परमेश्वर",
            "D": "भातदाल"
        }
    },
    {
        "id": "obj_56",
        "type": "objective",
        "question": "'पुत्रशोक' शब्द का समास-विग्रह क्या होगा ?",
        "prashna": "'पुत्रशोक' शब्द का समास-विग्रह क्या होगा ?",
        "options": {
            "A": "पुत्र और शोक",
            "B": "पुत्र से शोक",
            "C": "पुत्र के लिए शोक",
            "D": "पुत्र को शोक"
        },
        "vikalpa": {
            "A": "पुत्र और शोक",
            "B": "पुत्र से शोक",
            "C": "पुत्र के लिए शोक",
            "D": "पुत्र को शोक"
        }
    },
    {
        "id": "obj_57",
        "type": "objective",
        "question": "'प्रत्युपकार' शब्द किस समास का उदाहरण है ?",
        "prashna": "'प्रत्युपकार' शब्द किस समास का उदाहरण है ?",
        "options": {
            "A": "द्विगु समास",
            "B": "अव्ययीभाव समास",
            "C": "नञ् समास",
            "D": "द्वन्द्व समास"
        },
        "vikalpa": {
            "A": "द्विगु समास",
            "B": "अव्ययीभाव समास",
            "C": "नञ् समास",
            "D": "द्वन्द्व समास"
        }
    },
    {
        "id": "obj_58",
        "type": "objective",
        "question": "'गगनचुंबी' शब्द किस तत्पुरुष समास का उदाहरण है ?",
        "prashna": "'गगनचुंबी' शब्द किस तत्पुरुष समास का उदाहरण है ?",
        "options": {
            "A": "कर्म तत्पुरुष समास",
            "B": "करण तत्पुरुष समास",
            "C": "अपादान तत्पुरुष समास",
            "D": "अधिकरण तत्पुरुष समास"
        },
        "vikalpa": {
            "A": "कर्म तत्पुरुष समास",
            "B": "करण तत्पुरुष समास",
            "C": "अपादान तत्पुरुष समास",
            "D": "अधिकरण तत्पुरुष समास"
        }
    },
    {
        "id": "obj_59",
        "type": "objective",
        "question": "'गुड़ खाकर गुलगुले से परहेज' लोकोक्ति का अर्थ है",
        "prashna": "'गुड़ खाकर गुलगुले से परहेज' लोकोक्ति का अर्थ है",
        "options": {
            "A": "नाम बड़ा और काम छोटा",
            "B": "सामूहिक चेतना का अभाव",
            "C": "दिखावटी संयम",
            "D": "अकेले बड़ा काम संभव नहीं होता"
        },
        "vikalpa": {
            "A": "नाम बड़ा और काम छोटा",
            "B": "सामूहिक चेतना का अभाव",
            "C": "दिखावटी संयम",
            "D": "अकेले बड़ा काम संभव नहीं होता"
        }
    },
    {
        "id": "obj_60",
        "type": "objective",
        "question": "'सिर पर भूत सवार होना' मुहावरे का अर्थ है",
        "prashna": "'सिर पर भूत सवार होना' मुहावरे का अर्थ है",
        "options": {
            "A": "धुन सवार होना",
            "B": "सिर में दर्द होना",
            "C": "पागल हो जाना",
            "D": "भूत के साथ रहना"
        },
        "vikalpa": {
            "A": "धुन सवार होना",
            "B": "सिर में दर्द होना",
            "C": "पागल हो जाना",
            "D": "भूत के साथ रहना"
        }
    },
    {
        "id": "obj_61",
        "type": "objective",
        "question": "हिन्दी में अनुनासिक वर्णों की कितनी संख्या है ?",
        "prashna": "हिन्दी में अनुनासिक वर्णों की कितनी संख्या है ?",
        "options": {
            "A": "तीन",
            "B": "चार",
            "C": "पाँच",
            "D": "सात"
        },
        "vikalpa": {
            "A": "तीन",
            "B": "चार",
            "C": "पाँच",
            "D": "सात"
        }
    },
    {
        "id": "obj_62",
        "type": "objective",
        "question": "'क्ष' किन वर्णों के मेल से बना है ?",
        "prashna": "'क्ष' किन वर्णों के मेल से बना है ?",
        "options": {
            "A": "क् + ष",
            "B": "क + ष",
            "C": "क् + श",
            "D": "छ + अ"
        },
        "vikalpa": {
            "A": "क् + ष",
            "B": "क + ष",
            "C": "क् + श",
            "D": "छ + अ"
        }
    },
    {
        "id": "obj_63",
        "type": "objective",
        "question": "'ऋ' का उच्चारण-स्थान है",
        "prashna": "'ऋ' का उच्चारण-स्थान है",
        "options": {
            "A": "कंठ",
            "B": "तालु",
            "C": "मूर्द्धा",
            "D": "दंत"
        },
        "vikalpa": {
            "A": "कंठ",
            "B": "तालु",
            "C": "मूर्द्धा",
            "D": "दंत"
        }
    },
    {
        "id": "obj_64",
        "type": "objective",
        "question": "निम्न में कौन मूल स्वर है ?",
        "prashna": "निम्न में कौन मूल स्वर है ?",
        "options": {
            "A": "इ",
            "B": "ई",
            "C": "ऊ",
            "D": "ए"
        },
        "vikalpa": {
            "A": "इ",
            "B": "ई",
            "C": "ऊ",
            "D": "ए"
        }
    },
    {
        "id": "obj_65",
        "type": "objective",
        "question": "निम्न में कौन ऊष्म व्यंजन है ?",
        "prashna": "निम्न में कौन ऊष्म व्यंजन है ?",
        "options": {
            "A": "स",
            "B": "य",
            "C": "ज",
            "D": "छ"
        },
        "vikalpa": {
            "A": "स",
            "B": "य",
            "C": "ज",
            "D": "छ"
        }
    },
    {
        "id": "obj_66",
        "type": "objective",
        "question": "गुरु नानक किस धारा के प्रमुख कवि हैं ?",
        "prashna": "गुरु नानक किस धारा के प्रमुख कवि हैं ?",
        "options": {
            "A": "सगुण",
            "B": "निर्गुण",
            "C": "प्रेममार्गी",
            "D": "कृष्णमार्गी"
        },
        "vikalpa": {
            "A": "सगुण",
            "B": "निर्गुण",
            "C": "प्रेममार्गी",
            "D": "कृष्णमार्गी"
        }
    },
    {
        "id": "obj_67",
        "type": "objective",
        "question": "'प्रेमवाटिका' किसकी रचना है ?",
        "prashna": "'प्रेमवाटिका' किसकी रचना है ?",
        "options": {
            "A": "गुरु नानक",
            "B": "रसखान",
            "C": "घनानंद",
            "D": "सुमित्रानंदन पंत"
        },
        "vikalpa": {
            "A": "गुरु नानक",
            "B": "रसखान",
            "C": "घनानंद",
            "D": "सुमित्रानंदन पंत"
        }
    },
    {
        "id": "obj_68",
        "type": "objective",
        "question": "'स्वदेशी' शीर्षक कविता किससे संकलित है ?",
        "prashna": "'स्वदेशी' शीर्षक कविता किससे संकलित है ?",
        "options": {
            "A": "प्रेमघन सर्वस्व से",
            "B": "जीर्ण जनपद से",
            "C": "भारत प्रयाग से",
            "D": "प्रयाग रामागमन से"
        },
        "vikalpa": {
            "A": "प्रेमघन सर्वस्व से",
            "B": "जीर्ण जनपद से",
            "C": "भारत प्रयाग से",
            "D": "प्रयाग रामागमन से"
        }
    },
    {
        "id": "obj_69",
        "type": "objective",
        "question": "निम्न में कौन 'प्रेम की पीर' के कवि हैं ?",
        "prashna": "निम्न में कौन 'प्रेम की पीर' के कवि हैं ?",
        "options": {
            "A": "गुरु नानक",
            "B": "रसखान",
            "C": "घनानंद",
            "D": "सुमित्रानंदन पंत"
        },
        "vikalpa": {
            "A": "गुरु नानक",
            "B": "रसखान",
            "C": "घनानंद",
            "D": "सुमित्रानंदन पंत"
        }
    },
    {
        "id": "obj_70",
        "type": "objective",
        "question": "सुमित्रानंदन पंत का जन्म किस राज्य में हुआ था ?",
        "prashna": "सुमित्रानंदन पंत का जन्म किस राज्य में हुआ था ?",
        "options": {
            "A": "बिहार में",
            "B": "मध्य प्रदेश में",
            "C": "राजस्थान में",
            "D": "उत्तरांचल (उत्तराखंड) में"
        },
        "vikalpa": {
            "A": "बिहार में",
            "B": "मध्य प्रदेश में",
            "C": "राजस्थान में",
            "D": "उत्तरांचल (उत्तराखंड) में"
        }
    },
    {
        "id": "obj_71",
        "type": "objective",
        "question": "रामधारी सिंह 'दिनकर' का जन्म कब हुआ था ?",
        "prashna": "रामधारी सिंह 'दिनकर' का जन्म कब हुआ था ?",
        "options": {
            "A": "1905 ई० में",
            "B": "1900 ई० में",
            "C": "1911 ई० में",
            "D": "1908 ई० में"
        },
        "vikalpa": {
            "A": "1905 ई० में",
            "B": "1900 ई० में",
            "C": "1911 ई० में",
            "D": "1908 ई० में"
        }
    },
    {
        "id": "obj_72",
        "type": "objective",
        "question": "'अज्ञेय' का पूरा नाम क्या है ?",
        "prashna": "'अज्ञेय' का पूरा नाम क्या है ?",
        "options": {
            "A": "सदानंद 'अज्ञेय'",
            "B": "सच्चिदानंद हीरानंद वात्स्यायन 'अज्ञेय'",
            "C": "हीरानंद शास्त्री 'अज्ञेय'",
            "D": "सदानंद हीरलाल कौशिक 'अज्ञेय'"
        },
        "vikalpa": {
            "A": "सदानंद 'अज्ञेय'",
            "B": "सच्चिदानंद हीरानंद वात्स्यायन 'अज्ञेय'",
            "C": "हीरानंद शास्त्री 'अज्ञेय'",
            "D": "सदानंद हीरलाल कौशिक 'अज्ञेय'"
        }
    },
    {
        "id": "obj_73",
        "type": "objective",
        "question": "पर्यावरण, मनुष्य और सभ्यता के विनाश की कथा व्यक्त करती कविता निम्न में कौन है ?",
        "prashna": "पर्यावरण, मनुष्य और सभ्यता के विनाश की कथा व्यक्त करती कविता निम्न में कौन है ?",
        "options": {
            "A": "अक्षर-ज्ञान",
            "B": "लौटकर आऊँगा फिर",
            "C": "एक वृक्ष की हत्या",
            "D": "इनमें से कोई नहीं"
        },
        "vikalpa": {
            "A": "अक्षर-ज्ञान",
            "B": "लौटकर आऊँगा फिर",
            "C": "एक वृक्ष की हत्या",
            "D": "इनमें से कोई नहीं"
        }
    },
    {
        "id": "obj_74",
        "type": "objective",
        "question": "‘खेत हैं जहाँ धान के, बहती नदी’ - किस कविता की पंक्ति है ?",
        "prashna": "‘खेत हैं जहाँ धान के, बहती नदी’ - किस कविता की पंक्ति है ?",
        "options": {
            "A": "हिरोशिमा",
            "B": "अक्षर-ज्ञान",
            "C": "लौटकर आऊँगा फिर",
            "D": "हमारी नींद"
        },
        "vikalpa": {
            "A": "हिरोशिमा",
            "B": "अक्षर-ज्ञान",
            "C": "लौटकर आऊँगा फिर",
            "D": "हमारी नींद"
        }
    },
    {
        "id": "obj_75",
        "type": "objective",
        "question": "'अक्षर-ज्ञान' शीर्षक कविता में बेटे का 'क' कहाँ नहीं अंटता ?",
        "prashna": "'अक्षर-ज्ञान' शीर्षक कविता में बेटे का 'क' कहाँ नहीं अंटता ?",
        "options": {
            "A": "खिड़की में",
            "B": "गमले में",
            "C": "चौखटे में",
            "D": "घड़े में"
        },
        "vikalpa": {
            "A": "खिड़की में",
            "B": "गमले में",
            "C": "चौखटे में",
            "D": "घड़े में"
        }
    },
    {
        "id": "obj_76",
        "type": "objective",
        "question": "रेनर मारिया रिल्के के पिता का नाम क्या था ?",
        "prashna": "रेनर मारिया रिल्के के पिता का नाम क्या था ?",
        "options": {
            "A": "जोसेफ रिल्के",
            "B": "ओसेन रिल्के",
            "C": "नार्मन रिल्के",
            "D": "मोनेर रिल्के"
        },
        "vikalpa": {
            "A": "जोसेफ रिल्के",
            "B": "ओसेन रिल्के",
            "C": "नार्मन रिल्के",
            "D": "मोनेर रिल्के"
        }
    },
    {
        "id": "obj_77",
        "type": "objective",
        "question": "'निसंक' शब्द का अर्थ है",
        "prashna": "'निसंक' शब्द का अर्थ है",
        "options": {
            "A": "शंकायुक्त",
            "B": "शंकामुक्त",
            "C": "चेतावनी",
            "D": "सच्चा मन"
        },
        "vikalpa": {
            "A": "शंकायुक्त",
            "B": "शंकामुक्त",
            "C": "चेतावनी",
            "D": "सच्चा मन"
        }
    },
    {
        "id": "obj_78",
        "type": "objective",
        "question": "भीमराव अंबेडकर किनके प्रोत्साहन पर उच्च शिक्षा के लिए अमेरिका और लंदन गए ?",
        "prashna": "भीमराव अंबेडकर किनके प्रोत्साहन पर उच्च शिक्षा के लिए अमेरिका और लंदन गए ?",
        "options": {
            "A": "ग्वालियर नरेश के प्रोत्साहन पर",
            "B": "सिंधिया नरेश के प्रोत्साहन पर",
            "C": "मेवाड़ नरेश के प्रोत्साहन पर",
            "D": "बड़ौदा नरेश के प्रोत्साहन पर"
        },
        "vikalpa": {
            "A": "ग्वालियर नरेश के प्रोत्साहन पर",
            "B": "सिंधिया नरेश के प्रोत्साहन पर",
            "C": "मेवाड़ नरेश के प्रोत्साहन पर",
            "D": "बड़ौदा नरेश के प्रोत्साहन पर"
        }
    },
    {
        "id": "obj_79",
        "type": "objective",
        "question": "'आध्यात्मिक शिक्षा से मेरा मतलब ............ है।' रिक्त स्थान में क्या होगा ?",
        "prashna": "'आध्यात्मिक शिक्षा से मेरा मतलब ............ है।' रिक्त स्थान में क्या होगा ?",
        "options": {
            "A": "व्यावसायिक शिक्षा",
            "B": "रूढ़िवादी शिक्षा",
            "C": "हृदय की शिक्षा",
            "D": "वैज्ञानिक शिक्षा"
        },
        "vikalpa": {
            "A": "व्यावसायिक शिक्षा",
            "B": "रूढ़िवादी शिक्षा",
            "C": "हृदय की शिक्षा",
            "D": "वैज्ञानिक शिक्षा"
        }
    },
    {
        "id": "obj_80",
        "type": "objective",
        "question": "अमीरुद्दीन व शम्सुद्दीन के मामाद्वय कौन थे ?",
        "prashna": "अमीरुद्दीन व शम्सुद्दीन के मामाद्वय कौन थे ?",
        "options": {
            "A": "निजामुद्दीन खाँ तथा तारीफ खाँ",
            "B": "हजरत खाँ तथा बिलावत खाँ",
            "C": "सादिक हुसैन तथा अलीबख्श",
            "D": "नादिम हुसैन तथा इरफान"
        },
        "vikalpa": {
            "A": "निजामुद्दीन खाँ तथा तारीफ खाँ",
            "B": "हजरत खाँ तथा बिलावत खाँ",
            "C": "सादिक हुसैन तथा अलीबख्श",
            "D": "नादिम हुसैन तथा इरफान"
        }
    },
    {
        "id": "obj_81",
        "type": "objective",
        "question": "'लाभ की इच्छा' वाक्यखंड के लिए एक शब्द है",
        "prashna": "'लाभ की इच्छा' वाक्यखंड के लिए एक शब्द है",
        "options": {
            "A": "जिगीषा",
            "B": "बुभुक्षा",
            "C": "स्पर्द्धा",
            "D": "लिप्ससा"
        },
        "vikalpa": {
            "A": "जिगीषा",
            "B": "बुभुक्षा",
            "C": "स्पर्द्धा",
            "D": "लिप्ससा"
        }
    },
    {
        "id": "obj_82",
        "type": "objective",
        "question": "'जहाँ तक सध सके' वाक्यखंड के लिए एक शब्द है",
        "prashna": "'जहाँ तक सध सके' वाक्यखंड के लिए एक शब्द है",
        "options": {
            "A": "यथाशक्ति",
            "B": "सव्यसाची",
            "C": "समागम",
            "D": "यथासाध्य"
        },
        "vikalpa": {
            "A": "यथाशक्ति",
            "B": "सव्यसाची",
            "C": "समागम",
            "D": "यथासाध्य"
        }
    },
    {
        "id": "obj_83",
        "type": "objective",
        "question": "'ज्येष्ठ' शब्द का विलोम है",
        "prashna": "'ज्येष्ठ' शब्द का विलोम है",
        "options": {
            "A": "अनामका",
            "B": "प्रतिघात",
            "C": "कनिष्ठ",
            "D": "अग्रज"
        },
        "vikalpa": {
            "A": "अनामका",
            "B": "प्रतिघात",
            "C": "कनिष्ठ",
            "D": "अग्रज"
        }
    },
    {
        "id": "obj_84",
        "type": "objective",
        "question": "'गौरव' शब्द का विलोम है",
        "prashna": "'गौरव' शब्द का विलोम है",
        "options": {
            "A": "आगत",
            "B": "आगमन",
            "C": "पराजय",
            "D": "लाघव"
        },
        "vikalpa": {
            "A": "आगत",
            "B": "आगमन",
            "C": "पराजय",
            "D": "लाघव"
        }
    },
    {
        "id": "obj_85",
        "type": "objective",
        "question": "'जातीय' शब्द का विलोम है",
        "prashna": "'जातीय' शब्द का विलोम है",
        "options": {
            "A": "सात्त्विक",
            "B": "निकृष्ट",
            "C": "विजातीय",
            "D": "चिरंतन"
        },
        "vikalpa": {
            "A": "सात्त्विक",
            "B": "निकृष्ट",
            "C": "विजातीय",
            "D": "चिरंतन"
        }
    },
    {
        "id": "obj_86",
        "type": "objective",
        "question": "'ब्रह्मा' का पर्यायवाची शब्द है",
        "prashna": "'ब्रह्मा' का पर्यायवाची शब्द है",
        "options": {
            "A": "चतुरानन",
            "B": "चतुर्भुज",
            "C": "त्रिनेत्र",
            "D": "चन्द्रशेखर"
        },
        "vikalpa": {
            "A": "चतुरानन",
            "B": "चतुर्भुज",
            "C": "त्रिनेत्र",
            "D": "चन्द्रशेखर"
        }
    },
    {
        "id": "obj_87",
        "type": "objective",
        "question": "'राजा' का पर्यायवाची शब्द है",
        "prashna": "'राजा' का पर्यायवाची शब्द है",
        "options": {
            "A": "त्रियामा",
            "B": "तापस",
            "C": "केशरी",
            "D": "महीप"
        },
        "vikalpa": {
            "A": "त्रियामा",
            "B": "तापस",
            "C": "केशरी",
            "D": "महीप"
        }
    },
    {
        "id": "obj_88",
        "type": "objective",
        "question": "'सोना' का पर्यायवाची शब्द है",
        "prashna": "'सोना' का पर्यायवाची शब्द है",
        "options": {
            "A": "हाटक",
            "B": "सविता",
            "C": "पयोद",
            "D": "हेम"
        },
        "vikalpa": {
            "A": "हाटक",
            "B": "सविता",
            "C": "पयोद",
            "D": "हेम"
        }
    },
    {
        "id": "obj_89",
        "type": "objective",
        "question": "निम्नलिखित में कौन शुद्ध वाक्य है ?",
        "prashna": "निम्नलिखित में कौन शुद्ध वाक्य है ?",
        "options": {
            "A": "सभा में यह प्रस्ताव स्वीकार हुआ ।",
            "B": "यह लड़के ने दही गिरा दी ।",
            "C": "पटना में दंगा चल रही है ।",
            "D": "शीला ने ग्रंथ पढ़ा ।"
        },
        "vikalpa": {
            "A": "सभा में यह प्रस्ताव स्वीकार हुआ ।",
            "B": "यह लड़के ने दही गिरा दी ।",
            "C": "पटना में दंगा चल रही है ।",
            "D": "शीला ने ग्रंथ पढ़ा ।"
        }
    },
    {
        "id": "obj_90",
        "type": "objective",
        "question": "निम्नलिखित में कौन अशुद्ध शब्द है ?",
        "prashna": "निम्नलिखित में कौन अशुद्ध शब्द है ?",
        "options": {
            "A": "त्योहार",
            "B": "बीमारी",
            "C": "शताब्दी",
            "D": "स्थायी"
        },
        "vikalpa": {
            "A": "त्योहार",
            "B": "बीमारी",
            "C": "शताब्दी",
            "D": "स्थायी"
        }
    },
    {
        "id": "obj_91",
        "type": "objective",
        "question": "बल्लि अम्माल किस शीर्षक कहानी की पात्रा है ?",
        "prashna": "बल्लि अम्माल किस शीर्षक कहानी की पात्रा है ?",
        "options": {
            "A": "माँ",
            "B": "नगर",
            "C": "ढहते विश्वास",
            "D": "दही वाली मंगम्मा"
        },
        "vikalpa": {
            "A": "माँ",
            "B": "नगर",
            "C": "ढहते विश्वास",
            "D": "दही वाली मंगम्मा"
        }
    },
    {
        "id": "obj_92",
        "type": "objective",
        "question": "ईश्वर पेटलीकर किस भाषा के लोकप्रिय कथाकार हैं ?",
        "prashna": "ईश्वर पेटलीकर किस भाषा के लोकप्रिय कथाकार हैं ?",
        "options": {
            "A": "राजस्थानी",
            "B": "उड़िया",
            "C": "गुजराती",
            "D": "पहाड़ी"
        },
        "vikalpa": {
            "A": "राजस्थानी",
            "B": "उड़िया",
            "C": "गुजराती",
            "D": "पहाड़ी"
        }
    },
    {
        "id": "obj_93",
        "type": "objective",
        "question": "'ढहते विश्वास' में किस बाँध के टूटने का प्रसंग आया है ?",
        "prashna": "'ढहते विश्वास' में किस बाँध के टूटने का प्रसंग आया है ?",
        "options": {
            "A": "दलेई बाँध",
            "B": "फरक्का बाँध",
            "C": "सिरकुरा बाँध",
            "D": "भीमताल बाँध"
        },
        "vikalpa": {
            "A": "दलेई बाँध",
            "B": "फरक्का बाँध",
            "C": "सिरकुरा बाँध",
            "D": "भीमताल बाँध"
        }
    },
    {
        "id": "obj_94",
        "type": "objective",
        "question": "मंगम्मा को किसके साथ विवाद था ?",
        "prashna": "मंगम्मा को किसके साथ विवाद था ?",
        "options": {
            "A": "माँ जी के साथ",
            "B": "शहर के ग्राहक के साथ",
            "C": "बहू नजम्मा के साथ",
            "D": "पड़ोसी के साथ"
        },
        "vikalpa": {
            "A": "माँ जी के साथ",
            "B": "शहर के ग्राहक के साथ",
            "C": "बहू नजम्मा के साथ",
            "D": "पड़ोसी के साथ"
        }
    },
    {
        "id": "obj_95",
        "type": "objective",
        "question": "संतू मछली लेकर क्यों भागा ?",
        "prashna": "संतू मछली लेकर क्यों भागा ?",
        "options": {
            "A": "कुएँ में डालने के लिए",
            "B": "पकाने के लिए",
            "C": "दीदी के लिए",
            "D": "कुत्ता के लिए"
        },
        "vikalpa": {
            "A": "कुएँ में डालने के लिए",
            "B": "पकाने के लिए",
            "C": "दीदी के लिए",
            "D": "कुत्ता के लिए"
        }
    },
    {
        "id": "obj_96",
        "type": "objective",
        "question": "अमीरुद्दीन का जन्म कहाँ हुआ था ?",
        "prashna": "अमीरुद्दीन का जन्म कहाँ हुआ था ?",
        "options": {
            "A": "महाराष्ट्र में",
            "B": "बिहार में",
            "C": "उत्तर प्रदेश में",
            "D": "पश्चिम बंगाल में"
        },
        "vikalpa": {
            "A": "महाराष्ट्र में",
            "B": "बिहार में",
            "C": "उत्तर प्रदेश में",
            "D": "पश्चिम बंगाल में"
        }
    },
    {
        "id": "obj_97",
        "type": "objective",
        "question": "विनोद कुमार शुक्ल के उपन्यास का नाम है",
        "prashna": "विनोद कुमार शुक्ल के उपन्यास का नाम है",
        "options": {
            "A": "सबकुछ होना बचा रहेगा",
            "B": "अतिरिक्त नहीं",
            "C": "नौकर की कमीज",
            "D": "महाविद्यालय"
        },
        "vikalpa": {
            "A": "सबकुछ होना बचा रहेगा",
            "B": "अतिरिक्त नहीं",
            "C": "नौकर की कमीज",
            "D": "महाविद्यालय"
        }
    },
    {
        "id": "obj_98",
        "type": "objective",
        "question": "अशोक वाजपेयी के माता-पिता का नाम क्या था ?",
        "prashna": "अशोक वाजपेयी के माता-पिता का नाम क्या था ?",
        "options": {
            "A": "सुमित्रा देवी और पूर्णानंद वाजपेयी",
            "B": "आसरा देवी और शिव वाजपेयी",
            "C": "कमला देवी और प्रफुल्ल वाजपेयी",
            "D": "निर्मला देवी और परमानंद वाजपेयी"
        },
        "vikalpa": {
            "A": "सुमित्रा देवी और पूर्णानंद वाजपेयी",
            "B": "आसरा देवी और शिव वाजपेयी",
            "C": "कमला देवी और प्रफुल्ल वाजपेयी",
            "D": "निर्मला देवी और परमानंद वाजपेयी"
        }
    },
    {
        "id": "obj_99",
        "type": "objective",
        "question": "सुलोचना कौन थी ?",
        "prashna": "सुलोचना कौन थी ?",
        "options": {
            "A": "लेखिका",
            "B": "कवयित्री",
            "C": "अभिनेत्री",
            "D": "हलवाइन"
        },
        "vikalpa": {
            "A": "लेखिका",
            "B": "कवयित्री",
            "C": "अभिनेत्री",
            "D": "हलवाइन"
        }
    },
    {
        "id": "obj_100",
        "type": "objective",
        "question": "“एक भाषा बोलनेवाली जाति की तरह अनेक भाषाएँ बोलनेवाले राष्ट्र की भी अस्मिता होती है।” यह किस शीर्षक पाठ की पंक्ति है ?",
        "prashna": "“एक भाषा बोलनेवाली जाति की तरह अनेक भाषाएँ बोलनेवाले राष्ट्र की भी अस्मिता होती है।” यह किस शीर्षक पाठ की पंक्ति है ?",
        "options": {
            "A": "भारत से हम क्या सीखें",
            "B": "नाखून क्यों बढ़ते हैं",
            "C": "नागरी लिपि",
            "D": "परंपरा का मूल्यांकन"
        },
        "vikalpa": {
            "A": "भारत से हम क्या सीखें",
            "B": "नाखून क्यों बढ़ते हैं",
            "C": "नागरी लिपि",
            "D": "परंपरा का मूल्यांकन"
        }
    },
    {
        "id": "gadyansh_1_1",
        "type": "comprehension",
        "instructions": "निम्नलिखित गद्यांशों में से किसी एक गद्यांश को पढ़कर नीचे दिए गए प्रश्नों के उत्तर दें। प्रत्येक प्रश्न दो अंकों का है।",
        "context": "(क) उद्योग का सामान्य अर्थ है प्राथमिक उत्पाद को गौण उत्पाद में परिवर्तित करना । औद्योगिक विकास देश की आर्थिक सम्पन्नता का मापदण्ड होता है । विश्व के प्राय: सभी उन्नत देश जैसे - संयुक्त राज्य अमेरिका, जापान, ब्रिटेन, रूस आदि औद्योगिक दृष्टि से सम्पन्न राष्ट्र हैं । भारत में औद्योगिक विकास का इतिहास अति प्राचीन है, लेकिन विकास की गति काफी धीमी रही है । आधुनिक उद्योगों की स्थापना मुख्यत: औपनिवेशिक काल में प्रारम्भ हुई, परन्तु इस समय उद्योग का स्थानीयकरण कुछ ही केन्द्रों पर सिमट कर रहा गया है । लघु और कुटीर उद्योगों का भारत के औद्योगिक उत्पादन में विशेष महत्त्व है, इसलिए इसके विकास पर भी विशेष ध्यान दिया गया । भारत ने उपलब्ध संसाधनों और औद्योगिक आवश्यकताओं को देखते हुए औद्योगिक विकास की नीतियां बनाई हैं ।",
        "sub_questions": {
            "(i)": "उद्योग का सामान्य अर्थ क्या है ?",
            "(ii)": "औद्योगिक दृष्टि से कौन-कौन राष्ट्र सम्पन्न हैं ?",
            "(iii)": "भारत के औद्योगिक उत्पादन में किनका विशेष महत्त्व है ?",
            "(iv)": "भारत ने औद्योगिक विकास की नीतियां क्या देखते हुए बनाई हैं ?",
            "(v)": "उपर्युक्त गद्यांश का एक समुचित शीर्षक दें ।"
        },
        "anuprashna": {
            "(i)": "उद्योग का सामान्य अर्थ क्या है ?",
            "(ii)": "औद्योगिक दृष्टि से कौन-कौन राष्ट्र सम्पन्न हैं ?",
            "(iii)": "भारत के औद्योगिक उत्पादन में किनका विशेष महत्त्व है ?",
            "(iv)": "भारत ने औद्योगिक विकास की नीतियां क्या देखते हुए बनाई हैं ?",
            "(v)": "उपर्युक्त गद्यांश का एक समुचित शीर्षक दें ।"
        }
    },
    {
        "id": "gadyansh_1_2",
        "type": "comprehension",
        "instructions": "निम्नलिखित गद्यांशों में से किसी एक गद्यांश को पढ़कर नीचे दिए गए प्रश्नों के उत्तर दें। प्रत्येक प्रश्न दो अंकों का है।",
        "context": "(ख) हिन्दी साहित्य को गद्य-पद्य और चम्पू तीन भागों में बाँटा गया है। गद्य और पद्य ही मुख्य रूप से हिन्दी साहित्य का आधार है। इन्हीं दो रूपों में हिन्दी साहित्य ने कई कीर्तिमान स्थापित किये हैं । संस्कृत साहित्य में चंपू का विशिष्ट स्थान रहा है; किन्तु हिन्दी साहित्य में इसकी उपस्थिति न के बराबर है । हिन्दी साहित्य में जयशंकर प्रसाद रचित 'उर्वशी' चंपू रचना है। आधुनिक युग में गद्य साहित्य का विकास तेज़ी से होने के कारण इस युग को गद्यकाल के नाम से भी जाना जाता है। गद्य में विचारों की प्रधानता होती है जबकि पद्य में भावों की। गद्य और पद्य मिश्रित रचना को ही चंपू कहते हैं।",
        "sub_questions": {
            "(i)": "हिन्दी साहित्य को कितने भागों में बाँटा गया है ?",
            "(ii)": "हिन्दी साहित्य का मुख्य आधार क्या है ?",
            "(iii)": "'उर्वशी' चंपू रचना किसकी है ?",
            "(iv)": "आधुनिक युग को किस नाम से जाना जाता है और क्यों ?",
            "(v)": "चंपू किसे कहते हैं ?"
        },
        "anuprashna": {
            "(i)": "हिन्दी साहित्य को कितने भागों में बाँटा गया है ?",
            "(ii)": "हिन्दी साहित्य का मुख्य आधार क्या है ?",
            "(iii)": "'उर्वशी' चंपू रचना किसकी है ?",
            "(iv)": "आधुनिक युग को किस नाम से जाना जाता है और क्यों ?",
            "(v)": "चंपू किसे कहते हैं ?"
        }
    },
    {
        "id": "gadyansh_2_1",
        "type": "comprehension",
        "instructions": "निम्नलिखित गद्यांशों में से किसी एक गद्यांश को पढ़कर नीचे दिए गए प्रश्नों के उत्तर दें। प्रत्येक प्रश्न दो अंकों का है।",
        "context": "(क) नेपाल, भारत के उत्तर में स्थित एक पड़ोसी देश है । इसका पूर्व-पश्चिम विस्तार अधिक है तथा उत्तर-दक्षिण विस्तार कम है । नेपाल के तीन ओर भारत के राज्य हैं । नेपाल के पूर्व में सिक्किम एवं पश्चिम बंगाल, पश्चिम में उत्तराखण्ड तथा दक्षिण में बिहार एवं उत्तर प्रदेश राज्य स्थित हैं । नेपाल की संरचना एवं स्थलाकृति को हिमालय की उत्पत्ति ने काफी प्रभावित किया है । नेपाल के उत्तरी भाग में अनेक ऊँचे-ऊँचे पर्वत शिखर हैं । विश्व का सर्वोच्च शिखर माउण्ट एवरेस्ट नेपाल में ही स्थित है । नेपाल में माउण्ट एवरेस्ट को सागरमाथा के नाम से पुकारा जाता है ।",
        "sub_questions": {
            "(i)": "भारत के उत्तर में स्थित पड़ोसी देश का नाम क्या है ?",
            "(ii)": "नेपाल के दक्षिण में कौन-कौन राज्य स्थित हैं ?",
            "(iii)": "नेपाल की संरचना एवं स्थलाकृति को किसने प्रभावित किया ?",
            "(iv)": "माउण्ट एवरेस्ट कहाँ स्थित है ?",
            "(v)": "सागरमाथा के नाम से किसको पुकारा जाता है ?"
        },
        "anuprashna": {
            "(i)": "भारत के उत्तर में स्थित पड़ोसी देश का नाम क्या है ?",
            "(ii)": "नेपाल के दक्षिण में कौन-कौन राज्य स्थित हैं ?",
            "(iii)": "नेपाल की संरचना एवं स्थलाकृति को किसने प्रभावित किया ?",
            "(iv)": "माउण्ट एवरेस्ट कहाँ स्थित है ?",
            "(v)": "सागरमाथा के नाम से किसको पुकारा जाता है ?"
        }
    },
    {
        "id": "gadyansh_2_2",
        "type": "comprehension",
        "instructions": "निम्नलिखित गद्यांशों में से किसी एक गद्यांश को पढ़कर नीचे दिए गए प्रश्नों के उत्तर दें। प्रत्येक प्रश्न दो अंकों का है।",
        "context": "(ख) डॉ० राजेन्द्र प्रसाद भारत के प्रथम राष्ट्रपति थे। इनका जन्म बिहार में हुआ था। इनके पिता का नाम महादेव सहाय तथा माता का नाम कमलेश्वरी देवी था। महादेव सहाय संस्कृत एवं फारसी के विद्वान थे। डॉ० राजेन्द्र प्रसाद भारतीय संविधान सभा के अध्यक्ष थे। कुशल राजनीतिज्ञ होने के साथ-साथ डॉ० राजेन्द्र प्रसाद प्रतिभा सम्पन्न साहित्यकार भी थे। उन्होंने 'बापू के कदमों में' एवं 'चम्पारण में महात्मा गांधी' आदि महत्त्वपूर्ण पुस्तकें लिखीं। डॉ० राजेन्द्र प्रसाद की साहित्यिक भाषा सरल, सहज एवं प्रभावोत्पादक है। एक समय में डॉ० राजेन्द्र प्रसाद सफल अधिवक्ता भी रहे हैं। देश के लिए उनका त्याग और समर्पण देश के युवाओं के लिए अनुकरणीय है ।",
        "sub_questions": {
            "(i)": "भारत के प्रथम राष्ट्रपति कौन थे ?",
            "(ii)": "डॉ० राजेन्द्र प्रसाद का जन्म कहाँ हुआ था ?",
            "(iii)": "डॉ० राजेन्द्र प्रसाद के माता-पिता का नाम क्या था ?",
            "(iv)": "संविधान सभा के अध्यक्ष कौन थे ?",
            "(v)": "डॉ० राजेन्द्र प्रसाद ने कौन-सी महत्त्वपूर्ण पुस्तकें लिखीं ?"
        },
        "anuprashna": {
            "(i)": "भारत के प्रथम राष्ट्रपति कौन थे ?",
            "(ii)": "डॉ० राजेन्द्र प्रसाद का जन्म कहाँ हुआ था ?",
            "(iii)": "डॉ० राजेन्द्र प्रसाद के माता-पिता का नाम क्या था ?",
            "(iv)": "संविधान सभा के अध्यक्ष कौन थे ?",
            "(v)": "डॉ० राजेन्द्र प्रसाद ने कौन-सी महत्त्वपूर्ण पुस्तकें लिखीं ?"
        }
    },
    {
        "id": "nibandh_1",
        "type": "essay",
        "instructions": "निम्नलिखित में से किसी एक विषय पर दिए गए संकेत बिंदुओं के आधार पर लगभग 250 - 300 शब्दों में निबंध लिखें :",
        "question": "विषय: (क) हमारा राष्ट्रीय ध्वज (i) प्रस्तावना (ii) भारतीय राष्ट्रीय ध्वज का इतिहास (iii) भारतीय राष्ट्रीय ध्वज का महत्त्व (iv) उपसंहार; (ख) गंगा नदी (i) परिचय (ii) धार्मिक दृष्टि से महत्त्व (iii) प्रदूषण की समस्या (iv) सफाई के लिए अभियान (v) निष्कर्ष; (ग) मेरे प्रिय कवि सूरदास (i) जीवन परिचय (ii) साहित्यिक परिचय (iii) हिन्दी साहित्य में महत्त्वपूर्ण स्थान (iv) उपसंहार; (घ) आदर्श अध्यापक (i) भूमिका (ii) अध्ययनशीलता (iii) चरित्रवान (iv) वर्तमान में अध्यापकों की स्थिति (v) उपसंहार; (ङ) दीपावली (i) प्रस्तावना (ii) दीपावली कब और क्यों मनाते हैं ? (iii) लाभ-हानि (iv) निष्कर्ष",
        "prashna": "विषय: (क) हमारा राष्ट्रीय ध्वज (i) प्रस्तावना (ii) भारतीय राष्ट्रीय ध्वज का इतिहास (iii) भारतीय राष्ट्रीय ध्वज का महत्त्व (iv) उपसंहार; (ख) गंगा नदी (i) परिचय (ii) धार्मिक दृष्टि से महत्त्व (iii) प्रदूषण की समस्या (iv) सफाई के लिए अभियान (v) निष्कर्ष; (ग) मेरे प्रिय कवि सूरदास (i) जीवन परिचय (ii) साहित्यिक परिचय (iii) हिन्दी साहित्य में महत्त्वपूर्ण स्थान (iv) उपसंहार; (घ) आदर्श अध्यापक (i) भूमिका (ii) अध्ययनशीलता (iii) चरित्रवान (iv) वर्तमान में अध्यापकों की स्थिति (v) उपसंहार; (ङ) दीपावली (i) प्रस्तावना (ii) दीपावली कब और क्यों मनाते हैं ? (iii) लाभ-हानि (iv) निष्कर्ष"
    },
    {
        "id": "patra_1_1",
        "type": "letter_writing",
        "instructions": "4. अपने प्रखंड के प्रमुख के पास एक पत्र लिखें जिसमें सड़क बनवाने का अनुरोध हो। अथवा मित्रता के महत्त्व पर दो छात्रों के बीच होनेवाले संवाद को लिखें।",
        "question": "अपने प्रखंड के प्रमुख के पास एक पत्र लिखें जिसमें सड़क बनवाने का अनुरोध हो।",
        "prashna": "अपने प्रखंड के प्रमुख के पास एक पत्र लिखें जिसमें सड़क बनवाने का अनुरोध हो।"
    },
    {
        "id": "patra_1_2",
        "type": "letter_writing",
        "instructions": "4. अपने प्रखंड के प्रमुख के पास एक पत्र लिखें जिसमें सड़क बनवाने का अनुरोध हो। अथवा मित्रता के महत्त्व पर दो छात्रों के बीच होनेवाले संवाद को लिखें।",
        "question": "मित्रता के महत्त्व पर दो छात्रों के बीच होनेवाले संवाद को लिखें।",
        "prashna": "मित्रता के महत्त्व पर दो छात्रों के बीच होनेवाले संवाद को लिखें।"
    },
    {
        "id": "short_1",
        "type": "short_answer",
        "instructions": "निम्नलिखित प्रश्नों में से किन्हीं पाँच प्रश्नों के उत्तर दें : (5 x 2 = 10)",
        "question": "'तरुतल निवासिनी' के माध्यम से कवि सुमित्रानंदन पंत क्या कहना चाहते हैं ?",
        "prashna": "'तरुतल निवासिनी' के माध्यम से कवि सुमित्रानंदन पंत क्या कहना चाहते हैं ?"
    },
    {
        "id": "short_2",
        "type": "short_answer",
        "instructions": "निम्नलिखित प्रश्नों में से किन्हीं पाँच प्रश्नों के उत्तर दें : (5 x 2 = 10)",
        "question": "कवि घनानंद अपने आँसुओं को कहाँ पहुँचाना चाहते हैं और क्यों ?",
        "prashna": "कवि घनानंद अपने आँसुओं को कहाँ पहुँचाना चाहते हैं और क्यों ?"
    },
    {
        "id": "short_3",
        "type": "short_answer",
        "instructions": "निम्नलिखित प्रश्नों में से किन्हीं पाँच प्रश्नों के उत्तर दें : (5 x 2 = 10)",
        "question": "'मेरे बिना तुम प्रभु' शीर्षक कविता का प्रतिपाद्य क्या है ?",
        "prashna": "'मेरे बिना तुम प्रभु' शीर्षक कविता का प्रतिपाद्य क्या है ?"
    },
    {
        "id": "short_4",
        "type": "short_answer",
        "instructions": "निम्नलिखित प्रश्नों में से किन्हीं पाँच प्रश्नों के उत्तर दें : (5 x 2 = 10)",
        "question": "'प्रज्ज्वलित क्षण की दुपहरी' से कवि का आशय क्या है ?",
        "prashna": "'प्रज्ज्वलित क्षण की दुपहरी' से कवि का आशय क्या है ?"
    },
    {
        "id": "short_5",
        "type": "short_answer",
        "instructions": "निम्नलिखित प्रश्नों में से किन्हीं पाँच प्रश्नों के उत्तर दें : (5 x 2 = 10)",
        "question": "बाढ़ आने के पहले लक्ष्मी ने क्या किया ?",
        "prashna": "बाढ़ आने के पहले लक्ष्मी ने क्या किया ?"
    },
    {
        "id": "short_6",
        "type": "short_answer",
        "instructions": "निम्नलिखित प्रश्नों में से किन्हीं पाँच प्रश्नों के उत्तर दें : (5 x 2 = 10)",
        "question": "बहुओं की आपसी लड़ाई पर सीता (माँ) की कैसी प्रतिक्रिया होती है ?",
        "prashna": "बहुओं की आपसी लड़ाई पर सीता (माँ) की कैसी प्रतिक्रिया होती है ?"
    },
    {
        "id": "short_7",
        "type": "short_answer",
        "instructions": "निम्नलिखित प्रश्नों में से किन्हीं पाँच प्रश्नों के उत्तर दें : (5 x 2 = 10)",
        "question": "गाँधीजी के अनुसार, शिक्षा का जरूरी अंग क्या होना चाहिए ?",
        "prashna": "गाँधीजी के अनुसार, शिक्षा का जरूरी अंग क्या होना चाहिए ?"
    },
    {
        "id": "short_8",
        "type": "short_answer",
        "instructions": "निम्नलिखित प्रश्नों में से किन्हीं पाँच प्रश्नों के उत्तर दें : (5 x 2 = 10)",
        "question": "डॉ० भीमराव अंबेडकर के अनुसार किसी कार्य में दक्षता प्राप्त करने के लिए क्या अनिवार्य है ?",
        "prashna": "डॉ० भीमराव अंबेडकर के अनुसार किसी कार्य में दक्षता प्राप्त करने के लिए क्या अनिवार्य है ?"
    },
    {
        "id": "short_9",
        "type": "short_answer",
        "instructions": "निम्नलिखित प्रश्नों में से किन्हीं पाँच प्रश्नों के उत्तर दें : (5 x 2 = 10)",
        "question": "नाखून क्यों बढ़ते हैं ? यह प्रश्न लेखक के सामने कैसे उपस्थित हुआ ?",
        "prashna": "नाखून क्यों बढ़ते हैं ? यह प्रश्न लेखक के सामने कैसे उपस्थित हुआ ?"
    },
    {
        "id": "short_10",
        "type": "short_answer",
        "instructions": "निम्नलिखित प्रश्नों में से किन्हीं पाँच प्रश्नों के उत्तर दें : (5 x 2 = 10)",
        "question": "छंद किसे कहते हैं और छंद के कितने प्रकार होते हैं ?",
        "prashna": "छंद किसे कहते हैं और छंद के कितने प्रकार होते हैं ?"
    },
    {
        "id": "long_1_1",
        "type": "long_answer",
        "instructions": "निम्नलिखित प्रश्नों में से किसी एक प्रश्न का उत्तर लिखें (शब्द सीमा लगभग 100) : (1 x 5 = 5)",
        "question": "संस्कृत और दूसरी भारतीय भाषाओं के अध्ययन से पाश्चात्य जगत् को प्रमुख लाभ क्या-क्या हुए ?",
        "prashna": "संस्कृत और दूसरी भारतीय भाषाओं के अध्ययन से पाश्चात्य जगत् को प्रमुख लाभ क्या-क्या हुए ?"
    },
    {
        "id": "long_1_2",
        "type": "long_answer",
        "instructions": "निम्नलिखित प्रश्नों में से किसी एक प्रश्न का उत्तर लिखें (शब्द सीमा लगभग 100) : (1 x 5 = 5)",
        "question": "सप्रसंग व्याख्या करें : 'देवता कहीं सड़कों पर गिट्टी तोड़ रहे, देवता मिलेंगे खेतों में, खलिहानों में ।'",
        "prashna": "सप्रसंग व्याख्या करें : 'देवता कहीं सड़कों पर गिट्टी तोड़ रहे, देवता मिलेंगे खेतों में, खलिहानों में ।'"
    }
]